dbf2sql/__init__.py
dbf2sql/__main__.py
dbf2sql/__version__.py
dbf2sql/config/__init__.py
dbf2sql/config/settings.py
dbf2sql/constants.py
dbf2sql/main.py
dbf2sql/utils/__init__.py
dbf2sql/utils/colors.py
dbf2sql-0.1.1.dev3.dist-info/entry_points.txt
dbf2sql-0.1.1.dev3.dist-info/LICENSE
dbf2sql-0.1.1.dev3.dist-info/WHEEL
dbf2sql-0.1.1.dev3.dist-info/METADATA
dbf2sql-0.1.1.dev3.dist-info/RECORD
